<?xml version="0.25" encoding="utf-8"?>
<TextureAtlas imagePath="FinnAnim.png">
	<!-- Created with Adobe Animate version 22.0.2.168 -->
	<!-- http://www.adobe.com/products/animate.html -->
	<SubTexture name="Finn Animation yez0000" x="0" y="0" width="195" height="127.5" frameX="-20.25" frameY="-35" frameWidth="236.25" frameHeight="169.75"/>
	<SubTexture name="Finn Animation yez0001" x="0" y="0" width="195" height="127.5" frameX="-20.25" frameY="-35" frameWidth="236.25" frameHeight="169.75"/>
	<SubTexture name="Finn Animation yez0002" x="0" y="0" width="195" height="127.5" frameX="-20.25" frameY="-35" frameWidth="236.25" frameHeight="169.75"/>
	<SubTexture name="Finn Animation yez0003" x="0" y="0" width="195" height="127.5" frameX="-20.25" frameY="-35" frameWidth="236.25" frameHeight="169.75"/>
	<SubTexture name="Finn Animation yez0004" x="0" y="0" width="195" height="127.5" frameX="-20.25" frameY="-35" frameWidth="236.25" frameHeight="169.75"/>
	<SubTexture name="Finn Animation yez0005" x="0" y="0" width="195" height="127.5" frameX="-20.25" frameY="-35" frameWidth="236.25" frameHeight="169.75"/>
	<SubTexture name="Finn Animation yez0006" x="0" y="0" width="195" height="127.5" frameX="-20.25" frameY="-35" frameWidth="236.25" frameHeight="169.75"/>
	<SubTexture name="Finn Animation yez0007" x="0" y="0" width="195" height="127.5" frameX="-20.25" frameY="-35" frameWidth="236.25" frameHeight="169.75"/>
	<SubTexture name="Finn Animation yez0008" x="0" y="0" width="195" height="127.5" frameX="-20.25" frameY="-35" frameWidth="236.25" frameHeight="169.75"/>
	<SubTexture name="Finn Animation yez0009" x="0" y="0" width="195" height="127.5" frameX="-20.25" frameY="-35" frameWidth="236.25" frameHeight="169.75"/>
	<SubTexture name="Finn Animation yez0010" x="0" y="0" width="195" height="127.5" frameX="-20.25" frameY="-35" frameWidth="236.25" frameHeight="169.75"/>
	<SubTexture name="Finn Animation yez0011" x="0" y="0" width="195" height="127.5" frameX="-20.25" frameY="-35" frameWidth="236.25" frameHeight="169.75"/>
	<SubTexture name="Finn Animation yez0012" x="195" y="0" width="195" height="127" frameX="-20.25" frameY="-36" frameWidth="236.25" frameHeight="169.75"/>
	<SubTexture name="Finn Animation yez0013" x="195" y="0" width="195" height="127" frameX="-20.25" frameY="-36" frameWidth="236.25" frameHeight="169.75"/>
	<SubTexture name="Finn Animation yez0014" x="390" y="0" width="195" height="126.5" frameX="-20.25" frameY="-36.5" frameWidth="236.25" frameHeight="169.75"/>
	<SubTexture name="Finn Animation yez0015" x="390" y="0" width="195" height="126.5" frameX="-20.25" frameY="-36.5" frameWidth="236.25" frameHeight="169.75"/>
	<SubTexture name="Finn Animation yez0016" x="585" y="0" width="195" height="126.5" frameX="-20.25" frameY="-36.5" frameWidth="236.25" frameHeight="169.75"/>
	<SubTexture name="Finn Animation yez0017" x="585" y="0" width="195" height="126.5" frameX="-20.25" frameY="-36.5" frameWidth="236.25" frameHeight="169.75"/>
	<SubTexture name="Finn Animation yez0018" x="585" y="0" width="195" height="126.5" frameX="-20.25" frameY="-36.5" frameWidth="236.25" frameHeight="169.75"/>
	<SubTexture name="Finn Animation yez0019" x="780" y="0" width="195" height="127" frameX="-20.25" frameY="-35.5" frameWidth="236.25" frameHeight="169.75"/>
	<SubTexture name="Finn Animation yez0020" x="780" y="0" width="195" height="127" frameX="-20.25" frameY="-35.5" frameWidth="236.25" frameHeight="169.75"/>
	<SubTexture name="Finn Animation yez0021" x="975" y="0" width="195" height="128.5" frameX="-20.25" frameY="-33.25" frameWidth="236.25" frameHeight="169.75"/>
	<SubTexture name="Finn Animation yez0022" x="975" y="0" width="195" height="128.5" frameX="-20.25" frameY="-33.25" frameWidth="236.25" frameHeight="169.75"/>
	<SubTexture name="Finn Animation yez0023" x="1170" y="0" width="195" height="128.75" frameX="-20.25" frameY="-32.75" frameWidth="236.25" frameHeight="169.75"/>
	<SubTexture name="Finn Animation yez0024" x="1170" y="0" width="195" height="128.75" frameX="-20.25" frameY="-32.75" frameWidth="236.25" frameHeight="169.75"/>
	<SubTexture name="Finn Animation yez0025" x="1365" y="0" width="195" height="128.75" frameX="-20.25" frameY="-32.5" frameWidth="236.25" frameHeight="169.75"/>
	<SubTexture name="Finn Animation yez0026" x="1365" y="0" width="195" height="128.75" frameX="-20.25" frameY="-32.5" frameWidth="236.25" frameHeight="169.75"/>
	<SubTexture name="Finn Animation yez0027" x="1560" y="0" width="195" height="128.75" frameX="-20.25" frameY="-32.5" frameWidth="236.25" frameHeight="169.75"/>
	<SubTexture name="Finn Animation yez0028" x="1560" y="0" width="195" height="128.75" frameX="-20.25" frameY="-32.5" frameWidth="236.25" frameHeight="169.75"/>
	<SubTexture name="Finn Animation yez0029" x="1560" y="0" width="195" height="128.75" frameX="-20.25" frameY="-32.5" frameWidth="236.25" frameHeight="169.75"/>
	<SubTexture name="Finn Animation yez0030" x="1560" y="0" width="195" height="128.75" frameX="-20.25" frameY="-32.5" frameWidth="236.25" frameHeight="169.75"/>
	<SubTexture name="Finn Animation yez0031" x="1560" y="0" width="195" height="128.75" frameX="-20.25" frameY="-32.5" frameWidth="236.25" frameHeight="169.75"/>
	<SubTexture name="Finn Animation yez0032" x="1560" y="0" width="195" height="128.75" frameX="-20.25" frameY="-32.5" frameWidth="236.25" frameHeight="169.75"/>
	<SubTexture name="Finn Animation yez0033" x="1560" y="0" width="195" height="128.75" frameX="-20.25" frameY="-32.5" frameWidth="236.25" frameHeight="169.75"/>
	<SubTexture name="Finn Animation yez0034" x="1560" y="0" width="195" height="128.75" frameX="-20.25" frameY="-32.5" frameWidth="236.25" frameHeight="169.75"/>
	<SubTexture name="Finn Animation yez0035" x="1560" y="0" width="195" height="128.75" frameX="-20.25" frameY="-32.5" frameWidth="236.25" frameHeight="169.75"/>
	<SubTexture name="Finn Animation yez0036" x="1560" y="0" width="195" height="128.75" frameX="-20.25" frameY="-32.5" frameWidth="236.25" frameHeight="169.75"/>
	<SubTexture name="Finn Animation yez0037" x="1560" y="0" width="195" height="128.75" frameX="-20.25" frameY="-32.5" frameWidth="236.25" frameHeight="169.75"/>
	<SubTexture name="Finn Animation yez0038" x="1560" y="0" width="195" height="128.75" frameX="-20.25" frameY="-32.5" frameWidth="236.25" frameHeight="169.75"/>
	<SubTexture name="Finn Animation yez0039" x="1560" y="0" width="195" height="128.75" frameX="-20.25" frameY="-32.5" frameWidth="236.25" frameHeight="169.75"/>
	<SubTexture name="Finn Animation yez0040" x="1560" y="0" width="195" height="128.75" frameX="-20.25" frameY="-32.5" frameWidth="236.25" frameHeight="169.75"/>
	<SubTexture name="Finn Animation yez0041" x="1755" y="0" width="210.25" height="129" frameX="-13.25" frameY="-29" frameWidth="236.25" frameHeight="169.75"/>
	<SubTexture name="Finn Animation yez0042" x="0" y="129" width="226.5" height="129.25" frameX="-8.5" frameY="-36.75" frameWidth="236.25" frameHeight="169.75"/>
	<SubTexture name="Finn Animation yez0043" x="226.5" y="129" width="236.25" height="168.75" frameX="0" frameY="0" frameWidth="236.25" frameHeight="169.75"/>
	<SubTexture name="Finn Animation yez0044" x="462.75" y="129" width="235.5" height="168.75" frameX="-0.25" frameY="-1" frameWidth="236.25" frameHeight="169.75"/>
	<SubTexture name="Finn Animation yez0045" x="698.25" y="129" width="228.5" height="168.5" frameX="-6" frameY="-1.25" frameWidth="236.25" frameHeight="169.75"/>
	<SubTexture name="Finn Animation yez0046" x="926.75" y="129" width="228.5" height="165" frameX="-6" frameY="-2.75" frameWidth="236.25" frameHeight="169.75"/>
	<SubTexture name="Finn Animation yez0047" x="1155.25" y="129" width="199.75" height="142.5" frameX="-17.75" frameY="-23.5" frameWidth="236.25" frameHeight="169.75"/>
	<SubTexture name="Finn Animation yez0048" x="1355" y="129" width="228.5" height="165" frameX="-6" frameY="-2.75" frameWidth="236.25" frameHeight="169.75"/>
	<SubTexture name="Finn Animation yez0049" x="1583.5" y="129" width="202.5" height="141.5" frameX="-16.75" frameY="-22.75" frameWidth="236.25" frameHeight="169.75"/>
	<SubTexture name="Finn Animation yez0050" x="1786" y="129" width="228.5" height="165" frameX="-6" frameY="-2.75" frameWidth="236.25" frameHeight="169.75"/>
	<SubTexture name="Finn Animation yez0051" x="0" y="297.75" width="205.25" height="140.25" frameX="-15.5" frameY="-22.5" frameWidth="236.25" frameHeight="169.75"/>
	<SubTexture name="Finn Animation yez0052" x="205.25" y="297.75" width="208.75" height="139.25" frameX="-14" frameY="-22.5" frameWidth="236.25" frameHeight="169.75"/>
	<SubTexture name="Finn Animation yez0053" x="414" y="297.75" width="228.5" height="165" frameX="-6" frameY="-2.75" frameWidth="236.25" frameHeight="169.75"/>
	<SubTexture name="Finn Animation yez0054" x="642.5" y="297.75" width="228.5" height="165" frameX="-6" frameY="-1.75" frameWidth="236.25" frameHeight="169.75"/>
	<SubTexture name="Finn Animation yez0055" x="871" y="297.75" width="209.25" height="130.5" frameX="-13.75" frameY="-30.75" frameWidth="236.25" frameHeight="169.75"/>
	<SubTexture name="Finn Animation yez0056" x="871" y="297.75" width="209.25" height="130.5" frameX="-13.75" frameY="-30.75" frameWidth="236.25" frameHeight="169.75"/>
	<SubTexture name="Finn Animation yez0057" x="1080.25" y="297.75" width="209.25" height="130" frameX="-13.75" frameY="-31.5" frameWidth="236.25" frameHeight="169.75"/>
	<SubTexture name="Finn Animation yez0058" x="1080.25" y="297.75" width="209.25" height="130" frameX="-13.75" frameY="-31.5" frameWidth="236.25" frameHeight="169.75"/>
	<SubTexture name="Finn Animation yez0059" x="1289.5" y="297.75" width="209.25" height="139" frameX="-13.75" frameY="-23" frameWidth="236.25" frameHeight="169.75"/>
	<SubTexture name="Finn Animation yez0060" x="1498.75" y="297.75" width="209.25" height="140.25" frameX="-13.75" frameY="-21.75" frameWidth="236.25" frameHeight="169.75"/>
	<SubTexture name="Finn Animation yez0061" x="1708" y="297.75" width="209.25" height="140" frameX="-13.75" frameY="-22" frameWidth="236.25" frameHeight="169.75"/>
	<SubTexture name="Finn Animation yez0062" x="0" y="462.75" width="209.25" height="142.25" frameX="-13.75" frameY="-19.75" frameWidth="236.25" frameHeight="169.75"/>
</TextureAtlas>
